image_crawler_utils/__init__.py
image_crawler_utils/configs.py
image_crawler_utils/keyword.py
image_crawler_utils/log.py
image_crawler_utils/progress_bar.py
image_crawler_utils/utils.py
image_crawler_utils/classes/cookies.py
image_crawler_utils/classes/crawler_settings.py
image_crawler_utils/classes/downloader.py
image_crawler_utils/classes/image_info.py
image_crawler_utils/classes/parser.py
image_crawler_utils/image_downloader/__init__.py
image_crawler_utils/image_downloader/downloaders/core_downloader.py
image_crawler_utils/image_downloader/downloaders/general_downloader.py
image_crawler_utils/image_downloader/downloaders/pixiv_downloader.py
image_crawler_utils/image_downloader/downloaders/twitter_downloader.py
image_crawler_utils/stations/booru/__init__.py
image_crawler_utils/stations/booru/parser_assets/constants.py
image_crawler_utils/stations/booru/parser_assets/danbooru_keyword_parser.py
image_crawler_utils/stations/booru/parser_assets/gelbooru_keyword_parser.py
image_crawler_utils/stations/booru/parser_assets/image_info_processing.py
image_crawler_utils/stations/booru/parser_assets/moebooru_keyword_parser.py
image_crawler_utils/stations/booru/parser_assets/safebooru_keyword_parser.py
image_crawler_utils/stations/pixiv/__init__.py
image_crawler_utils/stations/pixiv/parser_assets/image_info_processing.py
image_crawler_utils/stations/pixiv/parser_assets/keyword_parser.py
image_crawler_utils/stations/pixiv/parser_assets/pixiv_cookies.py
image_crawler_utils/stations/pixiv/parser_assets/search_settings.py
image_crawler_utils/stations/pixiv/parser_assets/user_parser.py
image_crawler_utils/stations/twitter/__init__.py
image_crawler_utils/stations/twitter/parser_assets/constants.py
image_crawler_utils/stations/twitter/parser_assets/keyword_parser.py
image_crawler_utils/stations/twitter/parser_assets/search_settings.py
image_crawler_utils/stations/twitter/parser_assets/search_status_analyzer.py
image_crawler_utils/stations/twitter/parser_assets/status_classes.py
image_crawler_utils-0.4.5.dist-info/METADATA
image_crawler_utils-0.4.5.dist-info/WHEEL
image_crawler_utils-0.4.5.dist-info/top_level.txt
image_crawler_utils-0.4.5.dist-info/RECORD
