Metadata-Version: 2.4
Name: image-crawler-utils
Version: 0.4.5
Summary: A rather customizable image crawler structure, designed to download images with their information using multi-threading method. Besides, several wheels have been implemented to help better build a custom image crawler for yourself.
Author-email: AkihaTatsu <akihareinhardt@yeah.net>
Maintainer-email: AkihaTatsu <akihareinhardt@yeah.net>
Project-URL: Homepage, https://github.com/AkihaTatsu/image-crawler-utils
Project-URL: Source, https://github.com/AkihaTatsu/image-crawler-utils
Project-URL: Tracker, https://github.com/AkihaTatsu/image-crawler-utils/issues
Classifier: Development Status :: 3 - Alpha
Classifier: Intended Audience :: Developers
Classifier: Intended Audience :: Science/Research
Classifier: Topic :: Internet
Classifier: Programming Language :: Python :: 3
Requires-Python: >=3.9
Requires-Dist: bs4
Requires-Dist: dill
Requires-Dist: lxml
Requires-Dist: nodriver>=0.45.1
Requires-Dist: pathvalidate
Requires-Dist: Requests
Requires-Dist: rich
Requires-Dist: ua_generator
